flywheel_cli/__init__.py
flywheel_cli/bruker.py
flywheel_cli/commands/__init__.py
flywheel_cli/commands/deid.py
flywheel_cli/commands/editions.py
flywheel_cli/commands/essentials.py
flywheel_cli/commands/export_bids.py
flywheel_cli/commands/gears/__init__.py
flywheel_cli/commands/gears/gears_disable.py
flywheel_cli/commands/gears/gears_enable.py
flywheel_cli/commands/gears/gears_install.py
flywheel_cli/commands/gears/gears_list.py
flywheel_cli/commands/gears/gears_search.py
flywheel_cli/commands/gears/gears_show.py
flywheel_cli/commands/gears/gears_upgrade.py
flywheel_cli/commands/gears/rules_list.py
flywheel_cli/commands/gears/rules_upgrade.py
flywheel_cli/commands/import_bids.py
flywheel_cli/commands/import_bruker.py
flywheel_cli/commands/import_dicom.py
flywheel_cli/commands/import_folder.py
flywheel_cli/commands/import_parrec.py
flywheel_cli/commands/import_template.py
flywheel_cli/commands/ingest.py
flywheel_cli/commands/providers.py
flywheel_cli/commands/retry_job.py
flywheel_cli/commands/sync.py
flywheel_cli/config.py
flywheel_cli/console.py
flywheel_cli/errors.py
flywheel_cli/exchange/__init__.py
flywheel_cli/exchange/exchange_db.py
flywheel_cli/exchange/util.py
flywheel_cli/folder_impl.py
flywheel_cli/fwlogging.py
flywheel_cli/importers/__init__.py
flywheel_cli/importers/abstract_importer.py
flywheel_cli/importers/abstract_scanner.py
flywheel_cli/importers/audit_log.py
flywheel_cli/importers/bruker_scan.py
flywheel_cli/importers/container_factory.py
flywheel_cli/importers/dicom_scan.py
flywheel_cli/importers/file_scan.py
flywheel_cli/importers/folder.py
flywheel_cli/importers/match_util.py
flywheel_cli/importers/packfile.py
flywheel_cli/importers/parrec_scan.py
flywheel_cli/importers/progress_reporter.py
flywheel_cli/importers/slurp_scan.py
flywheel_cli/importers/template.py
flywheel_cli/importers/upload_queue.py
flywheel_cli/importers/work_queue.py
flywheel_cli/ingest/__init__.py
flywheel_cli/ingest/client/__init__.py
flywheel_cli-18.5.1.dist-info/LICENSE
flywheel_cli-18.5.1.dist-info/METADATA
flywheel_cli-18.5.1.dist-info/WHEEL
flywheel_cli-18.5.1.dist-info/entry_points.txt
flywheel_cli-18.5.1.dist-info/RECORD
