Metadata-Version: 2.1
Name: flywheel-cli
Version: 18.5.1
Summary: Flywheel Command Line Interface
Author: Flywheel
Author-email: support@flywheel.io
Requires-Python: >=3.10,<4.0
Classifier: Programming Language :: Python :: 3
Classifier: Programming Language :: Python :: 3.10
Classifier: Programming Language :: Python :: 3.11
Classifier: Programming Language :: Python :: 3.12
Requires-Dist: boto3 (>=1.0.0,<2.0.0)
Requires-Dist: charset-normalizer (==3.0.0)
Requires-Dist: crayons (>=0.0.0,<1.0.0)
Requires-Dist: flywheel-bids (>=1.2.10,<2.0.0)
Requires-Dist: flywheel-migration (>13.0.0,<14.0.0)
Requires-Dist: flywheel-sdk (>=17.0.0,<18.0.0)
Requires-Dist: fs (>=2.0.0,<3.0.0)
Requires-Dist: fw-http-client (>=1.0.0,<2.0.0)
Requires-Dist: fw-storage[az] (>=3.0.0)
Requires-Dist: fw-utils (>=4.0.0)
Requires-Dist: google-cloud-storage (>=2.0.0,<3.0.0)
Requires-Dist: keyring (==25.2.1)
Requires-Dist: pathvalidate (>=2.3.0,<3.0.0)
Requires-Dist: portalocker (==1.7.1)
Requires-Dist: psycopg2-binary (>=2.8.5,<3.0.0)
Requires-Dist: pydantic (>=2.0.0,<3.0.0)
Requires-Dist: pydantic-settings (>=2.0.0,<3.0.0)
Requires-Dist: python-dateutil (>=2.0.0,<3.0.0)
Requires-Dist: pytz (>=2023.0,<2024.0)
Requires-Dist: ruamel.yaml (>=0.18.0,<0.19.0)
Requires-Dist: sqlalchemy (>=1.3.19,<1.4.0)
Requires-Dist: sqlalchemy-utils (>=0,<1)
Requires-Dist: tqdm (>=4.0.0,<5.0.0)
Requires-Dist: tzlocal (>=5.0,<6.0)
Requires-Dist: urllib3 (<2.1.0)
Requires-Dist: wrapt (>=1.0.0,<2.0.0)
